MANIFEST.in
reporter.py
setup.py
prose_codeaccelerator.egg-info/PKG-INFO
prose_codeaccelerator.egg-info/SOURCES.txt
prose_codeaccelerator.egg-info/dependency_links.txt
prose_codeaccelerator.egg-info/top_level.txt